LICENSE
MANIFEST.in
README.rst
setup.py
djangocms_store_locator/__init__.py
djangocms_store_locator/admin.py
djangocms_store_locator/cms_plugins.py
djangocms_store_locator/models.py
djangocms_store_locator/settings.py
djangocms_store_locator/urls.py
djangocms_store_locator/views.py
djangocms_store_locator.egg-info/PKG-INFO
djangocms_store_locator.egg-info/SOURCES.txt
djangocms_store_locator.egg-info/dependency_links.txt
djangocms_store_locator.egg-info/not-zip-safe
djangocms_store_locator.egg-info/requires.txt
djangocms_store_locator.egg-info/top_level.txt
djangocms_store_locator/migrations/0001_initial.py
djangocms_store_locator/migrations/0002_auto__add_field_storelocator_append_to_search.py
djangocms_store_locator/migrations/__init__.py
djangocms_store_locator/static/.DS_Store
djangocms_store_locator/static/djangocms_store_locator/js/store_locator_admin.js
djangocms_store_locator/templates/djangocms_store_locator/store_locator_map.html