Metadata-Version: 1.1
Name: djangocms-store-locator
Version: 0.1.3
Summary: A simple store locator django CMS plugin that uses Google Maps.
Home-page: http://www.django-cms.org/
Author: Ales Kocjancic
Author-email: alesdotio@gmail.com
License: BSD License
Platform: OS Independent
Classifier: Environment :: Web Environment
Classifier: Framework :: Django
Classifier: Intended Audience :: Developers
Classifier: License :: OSI Approved :: BSD License
Classifier: Operating System :: OS Independent
Classifier: Programming Language :: Python
Classifier: Topic :: Software Development :: Libraries :: Application Frameworks
Classifier: Topic :: Internet :: WWW/HTTP :: Dynamic Content
